krixik/__base__.py
krixik/__init__.py
krixik/__version__.py
krixik/main.py
krixik/modules/__init__.py
krixik/modules/caption/__init__.py
krixik/modules/caption/io.py
krixik/modules/caption/models.py
krixik/modules/caption/module.yml
krixik/modules/json-to-txt/__init__.py
krixik/modules/json-to-txt/io.py
krixik/modules/json-to-txt/models.py
krixik/modules/json-to-txt/module.yml
krixik/modules/json-to-txt/params.py
krixik/modules/keyword-db/__init__.py
krixik/modules/keyword-db/io.py
krixik/modules/keyword-db/models.py
krixik/modules/keyword-db/module.yml
krixik/modules/ocr/__init__.py
krixik/modules/ocr/io.py
krixik/modules/ocr/models.py
krixik/modules/ocr/module.yml
krixik/modules/parser/__init__.py
krixik/modules/parser/io.py
krixik/modules/parser/models.py
krixik/modules/parser/module.yml
krixik/modules/parser/params.py
krixik/modules/sentiment/__init__.py
krixik/modules/sentiment/io.py
krixik/modules/sentiment/models.py
krixik/modules/sentiment/module.yml
krixik/modules/summarize/__init__.py
krixik/modules/summarize/io.py
krixik/modules/summarize/models.py
krixik/modules/summarize/module.yml
krixik/modules/text-embedder/__init__.py
krixik/modules/text-embedder/io.py
krixik/modules/text-embedder/models.py
krixik/modules/text-embedder/module.yml
krixik/modules/text-embedder/params.py
krixik/modules/transcribe/__init__.py
krixik/modules/transcribe/io.py
krixik/modules/transcribe/models.py
krixik/modules/transcribe/module.yml
krixik/modules/translate/__init__.py
krixik/modules/translate/io.py
krixik/modules/translate/models.py
krixik/modules/translate/module.yml
krixik/modules/utilities/__init__.py
krixik/modules/utilities/decorators.py
krixik/modules/utilities/io_validator.py
krixik/modules/utilities/model.py
krixik/modules/utilities/model_selection.py
krixik/modules/utilities/module_selections.py
krixik/modules/utilities/read_config.py
krixik/modules/vector-db/__init__.py
krixik/modules/vector-db/io.py
krixik/modules/vector-db/models.py
krixik-1.1.19.dist-info/METADATA
krixik-1.1.19.dist-info/WHEEL
krixik-1.1.19.dist-info/top_level.txt
krixik-1.1.19.dist-info/RECORD
