Metadata-Version: 2.1
Name: krixik
Version: 1.1.19
Summary: Easily assemble and serverlessly consume modular AI pipelines through secure Python APIs.
Home-page: https://github.com/krixik-ai/krixik-cli
Author: Jeremy Watt
License: UNKNOWN
Platform: UNKNOWN
Requires-Python: >=3.8
Requires-Dist: boto3
Requires-Dist: nltk
Requires-Dist: numpy
Requires-Dist: pillow
Requires-Dist: pyaml
Requires-Dist: pypdf
Requires-Dist: pytest
Requires-Dist: pytest-subtests
Requires-Dist: python-docx
Requires-Dist: python-dotenv
Requires-Dist: python-pptx
Requires-Dist: requests
Provides-Extra: linting
Requires-Dist: ruff; extra == "linting"
Provides-Extra: testing
Requires-Dist: pytest; extra == "testing"
Requires-Dist: pytest-xdist; extra == "testing"
Requires-Dist: boto3; extra == "testing"
Requires-Dist: nltk; extra == "testing"
Requires-Dist: numpy; extra == "testing"
Requires-Dist: pillow; extra == "testing"
Requires-Dist: pyaml; extra == "testing"
Requires-Dist: pypdf; extra == "testing"
Requires-Dist: pytest-subtests; extra == "testing"
Requires-Dist: python-docx; extra == "testing"
Requires-Dist: python-dotenv; extra == "testing"
Requires-Dist: python-pptx; extra == "testing"
Requires-Dist: requests; extra == "testing"
